rigidanalytics/__init__.py
rigidanalytics/_compat.py
rigidanalytics/_types.py
rigidanalytics/apps.py
rigidanalytics/middleware.py
rigidanalytics/transport.py
rigidanalytics/utils.py
rigidanalytics/worker.py
rigidanalytics_tracker_test-0.0.1.dist-info/LICENSE
rigidanalytics_tracker_test-0.0.1.dist-info/METADATA
rigidanalytics_tracker_test-0.0.1.dist-info/WHEEL
rigidanalytics_tracker_test-0.0.1.dist-info/top_level.txt
rigidanalytics_tracker_test-0.0.1.dist-info/RECORD
