Metadata-Version: 2.1
Name: rigidanalytics-tracker-test
Version: 0.0.1
Summary: Server-side analytics
Home-page: https://github.com/reustleco/rigidanalytics-tracker/
Author: Shane Reustle
Author-email: shane@reustle.co
License: MIT
Platform: UNKNOWN
Requires-Dist: urllib3
